[
    {
        "id": "1",
        "img": "@/../static/img/makeTj1.png"
    },
    {
        "id": "2",
        "img": "@/../static/img/makeTj2.png"
    },
    {
        "id": "3",
        "img": "@/../static/img/makeTj3.png"
    },
    {
        "id": "4",
        "img": "@/../static/img/makeTj4.png"
    },
    {
        "id": "5",
        "img": "@/../static/img/makeTj5.png"
    },
    {
        "id": "6",
        "img": "@/../static/img/makeTj6.png"
    },
    {
        "id": "7",
        "img": "@/../static/img/makeTj7.png"
    },
    {
        "id": "8",
        "img": "@/../static/img/makeTj8.png"
    }
]